sshJUNOS
