Metadata-Version: 1.0
Name: sshJUNOS
Version: 2.0
Summary: ssh module for Juniper OS
Home-page: https://github.com/FedericoOlivieri/networkAutomation/blob/master/python/modules/sshJUNOS/sshJUNOS/__init__.py
Author: Federico Olivieri
Author-email: lvrfrc87@gmail.com
License: MIT
Platform: UNKNOWN
